irrmc/__init__.py
irrmc/irrmontecarlo.py
irrmontecarlo-0.0.1.dist-info/METADATA
irrmontecarlo-0.0.1.dist-info/WHEEL
irrmontecarlo-0.0.1.dist-info/dependency_links.txt
irrmontecarlo-0.0.1.dist-info/top_level.txt
irrmontecarlo-0.0.1.dist-info/RECORD
